{
  "name": "Road Course - Config",
  "trackId": "129",
  "centerline": [
    {
      "x": 1641.1,
      "y": 259.8,
      "distPct": 0
    },
    {
      "x": 1637.86,
      "y": 238.06,
      "distPct": 0.0044
    },
    {
      "x": 1629.01,
      "y": 214.91,
      "distPct": 0.0094
    },
    {
      "x": 1610.65,
      "y": 190.65,
      "distPct": 0.0154
    },
    {
      "x": 1578.9,
      "y": 165.6,
      "distPct": 0.0235
    },
    {
      "x": 1578.6,
      "y": 165.4,
      "distPct": 0.0236
    },
    {
      "x": 1576.93,
      "y": 164.42,
      "distPct": 0.024
    },
    {
      "x": 1575.24,
      "y": 163.44,
      "distPct": 0.0244
    },
    {
      "x": 1573.52,
      "y": 162.43,
      "distPct": 0.0248
    },
    {
      "x": 1571.8,
      "y": 161.4,
      "distPct": 0.0252
    },
    {
      "x": 1539.65,
      "y": 143.06,
      "distPct": 0.0326
    },
    {
      "x": 1502.54,
      "y": 125.11,
      "distPct": 0.0408
    },
    {
      "x": 1462.86,
      "y": 112.28,
      "distPct": 0.0492
    },
    {
      "x": 1423.0,
      "y": 109.3,
      "distPct": 0.0572
    },
    {
      "x": 1396.61,
      "y": 114.55,
      "distPct": 0.0626
    },
    {
      "x": 1373.04,
      "y": 124.06,
      "distPct": 0.0676
    },
    {
      "x": 1351.77,
      "y": 136.15,
      "distPct": 0.0725
    },
    {
      "x": 1332.3,
      "y": 149.1,
      "distPct": 0.0772
    },
    {
      "x": 1323.73,
      "y": 154.91,
      "distPct": 0.0793
    },
    {
      "x": 1315.41,
      "y": 160.34,
      "distPct": 0.0813
    },
    {
      "x": 1307.34,
      "y": 165.15,
      "distPct": 0.0831
    },
    {
      "x": 1299.5,
      "y": 169.1,
      "distPct": 0.0849
    },
    {
      "x": 1299.3,
      "y": 169.2,
      "distPct": 0.085
    },
    {
      "x": 1257.25,
      "y": 180.95,
      "distPct": 0.0937
    },
    {
      "x": 1192.2,
      "y": 192.18,
      "distPct": 0.1069
    },
    {
      "x": 1125.57,
      "y": 200.14,
      "distPct": 0.1203
    },
    {
      "x": 1078.8,
      "y": 202.1,
      "distPct": 0.1297
    },
    {
      "x": 1053.54,
      "y": 198.08,
      "distPct": 0.1348
    },
    {
      "x": 1028.35,
      "y": 189.63,
      "distPct": 0.1401
    },
    {
      "x": 1005.11,
      "y": 179.18,
      "distPct": 0.1452
    },
    {
      "x": 985.7,
      "y": 169.2,
      "distPct": 0.1496
    },
    {
      "x": 980.23,
      "y": 166.36,
      "distPct": 0.1508
    },
    {
      "x": 975.36,
      "y": 163.88,
      "distPct": 0.1519
    },
    {
      "x": 971.12,
      "y": 161.8,
      "distPct": 0.1528
    },
    {
      "x": 967.5,
      "y": 160.2,
      "distPct": 0.1536
    },
    {
      "x": 966.87,
      "y": 159.96,
      "distPct": 0.1538
    },
    {
      "x": 966.17,
      "y": 159.69,
      "distPct": 0.1539
    },
    {
      "x": 965.45,
      "y": 159.4,
      "distPct": 0.1541
    },
    {
      "x": 964.7,
      "y": 159.1,
      "distPct": 0.1542
    },
    {
      "x": 943.31,
      "y": 151.86,
      "distPct": 0.1588
    },
    {
      "x": 909.55,
      "y": 148.94,
      "distPct": 0.1655
    },
    {
      "x": 863.56,
      "y": 159.87,
      "distPct": 0.175
    },
    {
      "x": 805.5,
      "y": 194.2,
      "distPct": 0.1885
    },
    {
      "x": 804.3,
      "y": 195.2,
      "distPct": 0.1888
    },
    {
      "x": 791.26,
      "y": 206.71,
      "distPct": 0.1923
    },
    {
      "x": 778.22,
      "y": 221.79,
      "distPct": 0.1963
    },
    {
      "x": 766.72,
      "y": 242.77,
      "distPct": 0.2011
    },
    {
      "x": 758.3,
      "y": 272.0,
      "distPct": 0.2071
    },
    {
      "x": 758.2,
      "y": 272.7,
      "distPct": 0.2073
    },
    {
      "x": 756.7,
      "y": 286.05,
      "distPct": 0.21
    },
    {
      "x": 753.82,
      "y": 311.59,
      "distPct": 0.2151
    },
    {
      "x": 750.47,
      "y": 341.45,
      "distPct": 0.2211
    },
    {
      "x": 747.5,
      "y": 367.8,
      "distPct": 0.2264
    },
    {
      "x": 747.4,
      "y": 368.5,
      "distPct": 0.2266
    },
    {
      "x": 738.15,
      "y": 404.58,
      "distPct": 0.234
    },
    {
      "x": 716.24,
      "y": 427.26,
      "distPct": 0.2403
    },
    {
      "x": 685.45,
      "y": 440.06,
      "distPct": 0.247
    },
    {
      "x": 649.6,
      "y": 446.5,
      "distPct": 0.2543
    },
    {
      "x": 647.1,
      "y": 446.8,
      "distPct": 0.2548
    },
    {
      "x": 584.73,
      "y": 455.42,
      "distPct": 0.2674
    },
    {
      "x": 533.64,
      "y": 463.66,
      "distPct": 0.2777
    },
    {
      "x": 494.45,
      "y": 471.4,
      "distPct": 0.2857
    },
    {
      "x": 467.8,
      "y": 478.5,
      "distPct": 0.2912
    },
    {
      "x": 438.22,
      "y": 489.11,
      "distPct": 0.2975
    },
    {
      "x": 409.11,
      "y": 501.69,
      "distPct": 0.3039
    },
    {
      "x": 384.68,
      "y": 515.67,
      "distPct": 0.3095
    },
    {
      "x": 369.1,
      "y": 530.5,
      "distPct": 0.3138
    },
    {
      "x": 365.94,
      "y": 535.97,
      "distPct": 0.3151
    },
    {
      "x": 362.87,
      "y": 542.34,
      "distPct": 0.3165
    },
    {
      "x": 359.85,
      "y": 549.36,
      "distPct": 0.318
    },
    {
      "x": 356.8,
      "y": 556.8,
      "distPct": 0.3196
    },
    {
      "x": 353.32,
      "y": 565.29,
      "distPct": 0.3215
    },
    {
      "x": 349.69,
      "y": 573.61,
      "distPct": 0.3233
    },
    {
      "x": 345.96,
      "y": 581.06,
      "distPct": 0.3249
    },
    {
      "x": 342.2,
      "y": 586.9,
      "distPct": 0.3263
    },
    {
      "x": 337.34,
      "y": 592.16,
      "distPct": 0.3278
    },
    {
      "x": 331.66,
      "y": 596.92,
      "distPct": 0.3292
    },
    {
      "x": 325.48,
      "y": 601.36,
      "distPct": 0.3308
    },
    {
      "x": 319.1,
      "y": 605.6,
      "distPct": 0.3323
    },
    {
      "x": 310.95,
      "y": 611.04,
      "distPct": 0.3343
    },
    {
      "x": 303.17,
      "y": 616.92,
      "distPct": 0.3362
    },
    {
      "x": 296.26,
      "y": 623.6,
      "distPct": 0.3381
    },
    {
      "x": 290.7,
      "y": 631.4,
      "distPct": 0.34
    },
    {
      "x": 280.33,
      "y": 659.68,
      "distPct": 0.3461
    },
    {
      "x": 280.79,
      "y": 688.31,
      "distPct": 0.3518
    },
    {
      "x": 292.18,
      "y": 717.79,
      "distPct": 0.3581
    },
    {
      "x": 314.6,
      "y": 748.6,
      "distPct": 0.3657
    },
    {
      "x": 314.8,
      "y": 748.9,
      "distPct": 0.3658
    },
    {
      "x": 337.88,
      "y": 775.04,
      "distPct": 0.3728
    },
    {
      "x": 372.25,
      "y": 815.26,
      "distPct": 0.3834
    },
    {
      "x": 403.62,
      "y": 852.36,
      "distPct": 0.3931
    },
    {
      "x": 417.7,
      "y": 869.1,
      "distPct": 0.3975
    },
    {
      "x": 418.0,
      "y": 869.4,
      "distPct": 0.3976
    },
    {
      "x": 431.89,
      "y": 883.25,
      "distPct": 0.4015
    },
    {
      "x": 446.39,
      "y": 896.44,
      "distPct": 0.4054
    },
    {
      "x": 461.47,
      "y": 908.93,
      "distPct": 0.4093
    },
    {
      "x": 477.1,
      "y": 920.7,
      "distPct": 0.4132
    },
    {
      "x": 500.16,
      "y": 935.12,
      "distPct": 0.4187
    },
    {
      "x": 524.62,
      "y": 946.84,
      "distPct": 0.4241
    },
    {
      "x": 550.25,
      "y": 955.76,
      "distPct": 0.4295
    },
    {
      "x": 576.8,
      "y": 961.8,
      "distPct": 0.435
    },
    {
      "x": 598.47,
      "y": 965.1,
      "distPct": 0.4394
    },
    {
      "x": 624.0,
      "y": 968.16,
      "distPct": 0.4445
    },
    {
      "x": 652.23,
      "y": 970.42,
      "distPct": 0.4502
    },
    {
      "x": 682.0,
      "y": 971.3,
      "distPct": 0.4561
    },
    {
      "x": 700.39,
      "y": 970.46,
      "distPct": 0.4598
    },
    {
      "x": 718.57,
      "y": 967.8,
      "distPct": 0.4635
    },
    {
      "x": 736.42,
      "y": 963.34,
      "distPct": 0.4672
    },
    {
      "x": 753.8,
      "y": 957.1,
      "distPct": 0.4709
    },
    {
      "x": 774.87,
      "y": 947.45,
      "distPct": 0.4755
    },
    {
      "x": 793.65,
      "y": 937.31,
      "distPct": 0.4798
    },
    {
      "x": 808.98,
      "y": 927.64,
      "distPct": 0.4834
    },
    {
      "x": 819.7,
      "y": 919.4,
      "distPct": 0.4861
    },
    {
      "x": 861.65,
      "y": 875.22,
      "distPct": 0.4983
    },
    {
      "x": 883.2,
      "y": 838.87,
      "distPct": 0.5067
    },
    {
      "x": 891.02,
      "y": 812.69,
      "distPct": 0.5122
    },
    {
      "x": 891.8,
      "y": 799.0,
      "distPct": 0.5149
    },
    {
      "x": 890.08,
      "y": 779.52,
      "distPct": 0.5189
    },
    {
      "x": 883.34,
      "y": 759.31,
      "distPct": 0.5231
    },
    {
      "x": 873.5,
      "y": 739.05,
      "distPct": 0.5276
    },
    {
      "x": 862.5,
      "y": 719.4,
      "distPct": 0.5321
    },
    {
      "x": 857.96,
      "y": 711.45,
      "distPct": 0.534
    },
    {
      "x": 853.81,
      "y": 703.91,
      "distPct": 0.5357
    },
    {
      "x": 850.28,
      "y": 697.0,
      "distPct": 0.5372
    },
    {
      "x": 847.6,
      "y": 690.9,
      "distPct": 0.5386
    },
    {
      "x": 846.08,
      "y": 683.93,
      "distPct": 0.54
    },
    {
      "x": 845.76,
      "y": 675.75,
      "distPct": 0.5416
    },
    {
      "x": 846.29,
      "y": 667.87,
      "distPct": 0.5432
    },
    {
      "x": 847.3,
      "y": 661.8,
      "distPct": 0.5444
    },
    {
      "x": 847.4,
      "y": 661.5,
      "distPct": 0.5445
    },
    {
      "x": 849.15,
      "y": 655.79,
      "distPct": 0.5457
    },
    {
      "x": 852.81,
      "y": 646.89,
      "distPct": 0.5476
    },
    {
      "x": 858.44,
      "y": 635.41,
      "distPct": 0.5502
    },
    {
      "x": 866.1,
      "y": 622.0,
      "distPct": 0.5533
    },
    {
      "x": 866.55,
      "y": 620.61,
      "distPct": 0.5536
    },
    {
      "x": 867.0,
      "y": 619.29,
      "distPct": 0.5538
    },
    {
      "x": 867.45,
      "y": 618.02,
      "distPct": 0.5541
    },
    {
      "x": 867.9,
      "y": 616.8,
      "distPct": 0.5544
    },
    {
      "x": 868.7,
      "y": 614.4,
      "distPct": 0.5549
    },
    {
      "x": 871.94,
      "y": 604.67,
      "distPct": 0.5569
    },
    {
      "x": 874.85,
      "y": 594.04,
      "distPct": 0.5591
    },
    {
      "x": 876.86,
      "y": 582.18,
      "distPct": 0.5615
    },
    {
      "x": 877.4,
      "y": 568.8,
      "distPct": 0.5642
    },
    {
      "x": 875.88,
      "y": 549.43,
      "distPct": 0.5681
    },
    {
      "x": 870.35,
      "y": 531.67,
      "distPct": 0.5718
    },
    {
      "x": 860.92,
      "y": 515.76,
      "distPct": 0.5755
    },
    {
      "x": 847.7,
      "y": 501.9,
      "distPct": 0.5794
    },
    {
      "x": 847.2,
      "y": 501.5,
      "distPct": 0.5795
    },
    {
      "x": 809.22,
      "y": 478.05,
      "distPct": 0.5884
    },
    {
      "x": 768.26,
      "y": 461.26,
      "distPct": 0.5973
    },
    {
      "x": 724.48,
      "y": 451.17,
      "distPct": 0.6063
    },
    {
      "x": 678.0,
      "y": 447.8,
      "distPct": 0.6156
    },
    {
      "x": 643.16,
      "y": 448.72,
      "distPct": 0.6226
    },
    {
      "x": 608.43,
      "y": 451.47,
      "distPct": 0.6295
    },
    {
      "x": 573.88,
      "y": 456.07,
      "distPct": 0.6365
    },
    {
      "x": 539.6,
      "y": 462.5,
      "distPct": 0.6435
    },
    {
      "x": 336.0,
      "y": 506.2,
      "distPct": 0.6851
    },
    {
      "x": 335.4,
      "y": 506.3,
      "distPct": 0.6853
    },
    {
      "x": 334.8,
      "y": 506.5,
      "distPct": 0.6854
    },
    {
      "x": 327.91,
      "y": 508.31,
      "distPct": 0.6868
    },
    {
      "x": 318.31,
      "y": 509.59,
      "distPct": 0.6887
    },
    {
      "x": 307.98,
      "y": 509.05,
      "distPct": 0.6908
    },
    {
      "x": 298.9,
      "y": 505.4,
      "distPct": 0.6928
    },
    {
      "x": 295.04,
      "y": 501.45,
      "distPct": 0.6939
    },
    {
      "x": 292.3,
      "y": 496.05,
      "distPct": 0.6951
    },
    {
      "x": 290.69,
      "y": 489.23,
      "distPct": 0.6965
    },
    {
      "x": 290.2,
      "y": 481.0,
      "distPct": 0.6981
    },
    {
      "x": 290.72,
      "y": 457.66,
      "distPct": 0.7028
    },
    {
      "x": 291.57,
      "y": 437.55,
      "distPct": 0.7068
    },
    {
      "x": 292.62,
      "y": 420.81,
      "distPct": 0.7102
    },
    {
      "x": 293.7,
      "y": 407.6,
      "distPct": 0.7128
    },
    {
      "x": 295.52,
      "y": 397.23,
      "distPct": 0.715
    },
    {
      "x": 299.11,
      "y": 387.42,
      "distPct": 0.717
    },
    {
      "x": 304.37,
      "y": 378.41,
      "distPct": 0.7191
    },
    {
      "x": 311.2,
      "y": 370.4,
      "distPct": 0.7212
    },
    {
      "x": 325.81,
      "y": 358.89,
      "distPct": 0.725
    },
    {
      "x": 343.66,
      "y": 349.65,
      "distPct": 0.729
    },
    {
      "x": 364.45,
      "y": 342.81,
      "distPct": 0.7334
    },
    {
      "x": 387.9,
      "y": 338.5,
      "distPct": 0.7381
    },
    {
      "x": 470.62,
      "y": 337.31,
      "distPct": 0.7547
    },
    {
      "x": 576.2,
      "y": 343.17,
      "distPct": 0.7758
    },
    {
      "x": 670.75,
      "y": 351.32,
      "distPct": 0.7948
    },
    {
      "x": 720.4,
      "y": 357.0,
      "distPct": 0.8048
    },
    {
      "x": 741.44,
      "y": 361.33,
      "distPct": 0.8091
    },
    {
      "x": 765.65,
      "y": 367.21,
      "distPct": 0.8141
    },
    {
      "x": 791.81,
      "y": 374.09,
      "distPct": 0.8195
    },
    {
      "x": 818.7,
      "y": 381.4,
      "distPct": 0.8251
    },
    {
      "x": 853.43,
      "y": 390.77,
      "distPct": 0.8323
    },
    {
      "x": 886.65,
      "y": 399.26,
      "distPct": 0.8391
    },
    {
      "x": 916.27,
      "y": 405.83,
      "distPct": 0.8452
    },
    {
      "x": 940.2,
      "y": 409.4,
      "distPct": 0.85
    },
    {
      "x": 960.18,
      "y": 410.21,
      "distPct": 0.854
    },
    {
      "x": 997.86,
      "y": 408.24,
      "distPct": 0.8616
    },
    {
      "x": 1041.94,
      "y": 398.67,
      "distPct": 0.8706
    },
    {
      "x": 1081.1,
      "y": 376.7,
      "distPct": 0.8796
    },
    {
      "x": 1091.84,
      "y": 364.88,
      "distPct": 0.8828
    },
    {
      "x": 1099.61,
      "y": 351.49,
      "distPct": 0.8859
    },
    {
      "x": 1104.4,
      "y": 336.58,
      "distPct": 0.889
    },
    {
      "x": 1106.2,
      "y": 320.2,
      "distPct": 0.8923
    },
    {
      "x": 1641.1,
      "y": 259.8,
      "distPct": 1.0
    }
  ],
  "bounds": {
    "xMin": 280.33,
    "xMax": 1641.1,
    "yMin": 109.3,
    "yMax": 971.3
  },
  "pointCount": 200,
  "source": "iTelemetry/iracing-tracks",
  "baseline": 0.473,
  "clockwise": false
}