{
  "name": "Grand Prix - Config",
  "trackId": "212",
  "centerline": [
    {
      "x": 1596.7,
      "y": 505.9,
      "distPct": 0
    },
    {
      "x": 1584.92,
      "y": 499.27,
      "distPct": 0.0025
    },
    {
      "x": 1572.49,
      "y": 492.12,
      "distPct": 0.0052
    },
    {
      "x": 1560.94,
      "y": 485.31,
      "distPct": 0.0077
    },
    {
      "x": 1551.8,
      "y": 479.7,
      "distPct": 0.0097
    },
    {
      "x": 1538.71,
      "y": 468.79,
      "distPct": 0.0128
    },
    {
      "x": 1533.46,
      "y": 458.45,
      "distPct": 0.015
    },
    {
      "x": 1533.79,
      "y": 448.48,
      "distPct": 0.0168
    },
    {
      "x": 1537.4,
      "y": 438.7,
      "distPct": 0.0188
    },
    {
      "x": 1553.53,
      "y": 389.25,
      "distPct": 0.0284
    },
    {
      "x": 1556.02,
      "y": 340.9,
      "distPct": 0.0374
    },
    {
      "x": 1544.91,
      "y": 293.83,
      "distPct": 0.0464
    },
    {
      "x": 1520.2,
      "y": 248.2,
      "distPct": 0.056
    },
    {
      "x": 1489.22,
      "y": 214.52,
      "distPct": 0.0645
    },
    {
      "x": 1449.77,
      "y": 189.75,
      "distPct": 0.0732
    },
    {
      "x": 1401.6,
      "y": 173.75,
      "distPct": 0.0826
    },
    {
      "x": 1344.4,
      "y": 166.4,
      "distPct": 0.0933
    },
    {
      "x": 1270.69,
      "y": 163.13,
      "distPct": 0.107
    },
    {
      "x": 1186.92,
      "y": 159.91,
      "distPct": 0.1226
    },
    {
      "x": 1095.55,
      "y": 156.71,
      "distPct": 0.1396
    },
    {
      "x": 999.0,
      "y": 153.5,
      "distPct": 0.1575
    },
    {
      "x": 905.3,
      "y": 150.37,
      "distPct": 0.175
    },
    {
      "x": 813.29,
      "y": 147.14,
      "distPct": 0.1921
    },
    {
      "x": 726.29,
      "y": 143.81,
      "distPct": 0.2082
    },
    {
      "x": 647.6,
      "y": 140.4,
      "distPct": 0.2229
    },
    {
      "x": 621.69,
      "y": 140.43,
      "distPct": 0.2277
    },
    {
      "x": 600.11,
      "y": 143.12,
      "distPct": 0.2317
    },
    {
      "x": 582.53,
      "y": 148.56,
      "distPct": 0.2351
    },
    {
      "x": 568.6,
      "y": 156.8,
      "distPct": 0.2381
    },
    {
      "x": 557.44,
      "y": 168.9,
      "distPct": 0.2412
    },
    {
      "x": 550.65,
      "y": 182.57,
      "distPct": 0.244
    },
    {
      "x": 547.08,
      "y": 196.74,
      "distPct": 0.2467
    },
    {
      "x": 545.6,
      "y": 210.3,
      "distPct": 0.2493
    },
    {
      "x": 545.3,
      "y": 232.93,
      "distPct": 0.2535
    },
    {
      "x": 546.39,
      "y": 259.99,
      "distPct": 0.2585
    },
    {
      "x": 548.2,
      "y": 287.63,
      "distPct": 0.2637
    },
    {
      "x": 550.1,
      "y": 312.0,
      "distPct": 0.2682
    },
    {
      "x": 550.31,
      "y": 314.29,
      "distPct": 0.2686
    },
    {
      "x": 550.49,
      "y": 316.49,
      "distPct": 0.269
    },
    {
      "x": 550.65,
      "y": 318.6,
      "distPct": 0.2694
    },
    {
      "x": 550.8,
      "y": 320.6,
      "distPct": 0.2698
    },
    {
      "x": 565.16,
      "y": 375.63,
      "distPct": 0.2804
    },
    {
      "x": 592.84,
      "y": 412.94,
      "distPct": 0.289
    },
    {
      "x": 626.27,
      "y": 437.02,
      "distPct": 0.2966
    },
    {
      "x": 657.9,
      "y": 452.4,
      "distPct": 0.3032
    },
    {
      "x": 661.2,
      "y": 453.8,
      "distPct": 0.3038
    },
    {
      "x": 692.94,
      "y": 467.72,
      "distPct": 0.3103
    },
    {
      "x": 729.22,
      "y": 483.15,
      "distPct": 0.3176
    },
    {
      "x": 768.92,
      "y": 499.78,
      "distPct": 0.3256
    },
    {
      "x": 810.9,
      "y": 517.3,
      "distPct": 0.3341
    },
    {
      "x": 865.5,
      "y": 540.06,
      "distPct": 0.345
    },
    {
      "x": 918.2,
      "y": 562.25,
      "distPct": 0.3557
    },
    {
      "x": 966.18,
      "y": 582.94,
      "distPct": 0.3654
    },
    {
      "x": 1006.6,
      "y": 601.2,
      "distPct": 0.3736
    },
    {
      "x": 1038.05,
      "y": 621.2,
      "distPct": 0.3805
    },
    {
      "x": 1055.24,
      "y": 642.41,
      "distPct": 0.3856
    },
    {
      "x": 1062.81,
      "y": 663.34,
      "distPct": 0.3897
    },
    {
      "x": 1065.4,
      "y": 682.5,
      "distPct": 0.3933
    },
    {
      "x": 1065.48,
      "y": 718.76,
      "distPct": 0.4001
    },
    {
      "x": 1058.34,
      "y": 748.76,
      "distPct": 0.4058
    },
    {
      "x": 1043.9,
      "y": 772.71,
      "distPct": 0.411
    },
    {
      "x": 1022.1,
      "y": 790.8,
      "distPct": 0.4162
    },
    {
      "x": 997.63,
      "y": 803.52,
      "distPct": 0.4214
    },
    {
      "x": 967.25,
      "y": 816.7,
      "distPct": 0.4275
    },
    {
      "x": 934.77,
      "y": 829.13,
      "distPct": 0.434
    },
    {
      "x": 904.0,
      "y": 839.6,
      "distPct": 0.44
    },
    {
      "x": 888.02,
      "y": 843.54,
      "distPct": 0.4431
    },
    {
      "x": 876.8,
      "y": 844.16,
      "distPct": 0.4452
    },
    {
      "x": 869.18,
      "y": 842.48,
      "distPct": 0.4466
    },
    {
      "x": 864.0,
      "y": 839.5,
      "distPct": 0.4477
    },
    {
      "x": 857.31,
      "y": 831.88,
      "distPct": 0.4496
    },
    {
      "x": 854.35,
      "y": 823.62,
      "distPct": 0.4512
    },
    {
      "x": 854.02,
      "y": 815.93,
      "distPct": 0.4527
    },
    {
      "x": 855.2,
      "y": 810.0,
      "distPct": 0.4538
    },
    {
      "x": 855.99,
      "y": 807.68,
      "distPct": 0.4542
    },
    {
      "x": 856.84,
      "y": 805.12,
      "distPct": 0.4547
    },
    {
      "x": 857.75,
      "y": 802.38,
      "distPct": 0.4553
    },
    {
      "x": 858.7,
      "y": 799.5,
      "distPct": 0.4558
    },
    {
      "x": 860.74,
      "y": 793.29,
      "distPct": 0.4571
    },
    {
      "x": 862.87,
      "y": 786.87,
      "distPct": 0.4583
    },
    {
      "x": 864.97,
      "y": 780.8,
      "distPct": 0.4595
    },
    {
      "x": 866.9,
      "y": 775.6,
      "distPct": 0.4605
    },
    {
      "x": 874.13,
      "y": 739.24,
      "distPct": 0.4674
    },
    {
      "x": 866.74,
      "y": 714.59,
      "distPct": 0.4722
    },
    {
      "x": 852.2,
      "y": 699.14,
      "distPct": 0.4761
    },
    {
      "x": 838.0,
      "y": 690.4,
      "distPct": 0.4792
    },
    {
      "x": 810.68,
      "y": 682.65,
      "distPct": 0.4845
    },
    {
      "x": 787.1,
      "y": 686.72,
      "distPct": 0.489
    },
    {
      "x": 768.84,
      "y": 697.52,
      "distPct": 0.4929
    },
    {
      "x": 757.5,
      "y": 709.9,
      "distPct": 0.496
    },
    {
      "x": 748.38,
      "y": 723.81,
      "distPct": 0.4991
    },
    {
      "x": 737.38,
      "y": 740.16,
      "distPct": 0.5028
    },
    {
      "x": 725.13,
      "y": 758.04,
      "distPct": 0.5068
    },
    {
      "x": 712.3,
      "y": 776.5,
      "distPct": 0.511
    },
    {
      "x": 710.4,
      "y": 779.2,
      "distPct": 0.5116
    },
    {
      "x": 698.84,
      "y": 795.5,
      "distPct": 0.5153
    },
    {
      "x": 687.91,
      "y": 809.82,
      "distPct": 0.5186
    },
    {
      "x": 677.45,
      "y": 821.42,
      "distPct": 0.5215
    },
    {
      "x": 667.3,
      "y": 829.5,
      "distPct": 0.524
    },
    {
      "x": 653.53,
      "y": 837.34,
      "distPct": 0.5269
    },
    {
      "x": 636.32,
      "y": 846.55,
      "distPct": 0.5305
    },
    {
      "x": 618.78,
      "y": 855.46,
      "distPct": 0.5342
    },
    {
      "x": 604.0,
      "y": 862.4,
      "distPct": 0.5372
    },
    {
      "x": 592.4,
      "y": 866.16,
      "distPct": 0.5395
    },
    {
      "x": 583.0,
      "y": 866.84,
      "distPct": 0.5412
    },
    {
      "x": 575.85,
      "y": 865.17,
      "distPct": 0.5426
    },
    {
      "x": 571.0,
      "y": 861.9,
      "distPct": 0.5437
    },
    {
      "x": 564.55,
      "y": 853.5,
      "distPct": 0.5456
    },
    {
      "x": 562.62,
      "y": 847.01,
      "distPct": 0.5469
    },
    {
      "x": 563.88,
      "y": 841.52,
      "distPct": 0.5479
    },
    {
      "x": 567.0,
      "y": 836.1,
      "distPct": 0.5491
    },
    {
      "x": 572.05,
      "y": 828.49,
      "distPct": 0.5508
    },
    {
      "x": 577.92,
      "y": 819.9,
      "distPct": 0.5527
    },
    {
      "x": 584.44,
      "y": 810.56,
      "distPct": 0.5549
    },
    {
      "x": 591.4,
      "y": 800.7,
      "distPct": 0.5571
    },
    {
      "x": 602.7,
      "y": 784.58,
      "distPct": 0.5608
    },
    {
      "x": 613.44,
      "y": 769.02,
      "distPct": 0.5643
    },
    {
      "x": 622.8,
      "y": 754.86,
      "distPct": 0.5674
    },
    {
      "x": 630.0,
      "y": 742.9,
      "distPct": 0.57
    },
    {
      "x": 643.95,
      "y": 714.22,
      "distPct": 0.5759
    },
    {
      "x": 652.34,
      "y": 687.96,
      "distPct": 0.5811
    },
    {
      "x": 655.38,
      "y": 663.15,
      "distPct": 0.5857
    },
    {
      "x": 653.3,
      "y": 638.8,
      "distPct": 0.5902
    },
    {
      "x": 637.25,
      "y": 596.17,
      "distPct": 0.5987
    },
    {
      "x": 611.49,
      "y": 565.84,
      "distPct": 0.6061
    },
    {
      "x": 582.1,
      "y": 545.83,
      "distPct": 0.6127
    },
    {
      "x": 555.2,
      "y": 534.2,
      "distPct": 0.6181
    },
    {
      "x": 542.96,
      "y": 529.96,
      "distPct": 0.6205
    },
    {
      "x": 529.14,
      "y": 525.14,
      "distPct": 0.6233
    },
    {
      "x": 514.1,
      "y": 519.84,
      "distPct": 0.6262
    },
    {
      "x": 498.2,
      "y": 514.2,
      "distPct": 0.6294
    },
    {
      "x": 465.84,
      "y": 502.8,
      "distPct": 0.6357
    },
    {
      "x": 433.57,
      "y": 491.51,
      "distPct": 0.6421
    },
    {
      "x": 403.67,
      "y": 481.22,
      "distPct": 0.648
    },
    {
      "x": 378.4,
      "y": 472.8,
      "distPct": 0.6529
    },
    {
      "x": 365.13,
      "y": 469.61,
      "distPct": 0.6554
    },
    {
      "x": 352.96,
      "y": 469.02,
      "distPct": 0.6577
    },
    {
      "x": 341.94,
      "y": 471.03,
      "distPct": 0.6598
    },
    {
      "x": 332.1,
      "y": 475.6,
      "distPct": 0.6618
    },
    {
      "x": 321.99,
      "y": 484.67,
      "distPct": 0.6643
    },
    {
      "x": 315.76,
      "y": 494.9,
      "distPct": 0.6665
    },
    {
      "x": 312.48,
      "y": 504.23,
      "distPct": 0.6684
    },
    {
      "x": 311.2,
      "y": 510.6,
      "distPct": 0.6696
    },
    {
      "x": 310.27,
      "y": 517.29,
      "distPct": 0.6708
    },
    {
      "x": 309.16,
      "y": 525.03,
      "distPct": 0.6723
    },
    {
      "x": 307.92,
      "y": 533.55,
      "distPct": 0.6739
    },
    {
      "x": 306.6,
      "y": 542.6,
      "distPct": 0.6756
    },
    {
      "x": 304.16,
      "y": 559.08,
      "distPct": 0.6787
    },
    {
      "x": 301.81,
      "y": 575.5,
      "distPct": 0.6818
    },
    {
      "x": 299.78,
      "y": 590.72,
      "distPct": 0.6846
    },
    {
      "x": 298.3,
      "y": 603.6,
      "distPct": 0.687
    },
    {
      "x": 296.85,
      "y": 625.18,
      "distPct": 0.691
    },
    {
      "x": 297.26,
      "y": 639.89,
      "distPct": 0.6938
    },
    {
      "x": 299.27,
      "y": 650.75,
      "distPct": 0.6958
    },
    {
      "x": 302.6,
      "y": 660.8,
      "distPct": 0.6978
    },
    {
      "x": 303.0,
      "y": 661.9,
      "distPct": 0.698
    },
    {
      "x": 312.5,
      "y": 685.86,
      "distPct": 0.7028
    },
    {
      "x": 324.26,
      "y": 712.56,
      "distPct": 0.7082
    },
    {
      "x": 336.79,
      "y": 738.39,
      "distPct": 0.7136
    },
    {
      "x": 348.6,
      "y": 759.7,
      "distPct": 0.7181
    },
    {
      "x": 372.87,
      "y": 797.19,
      "distPct": 0.7264
    },
    {
      "x": 392.65,
      "y": 824.45,
      "distPct": 0.7326
    },
    {
      "x": 409.57,
      "y": 845.03,
      "distPct": 0.7376
    },
    {
      "x": 425.3,
      "y": 862.5,
      "distPct": 0.742
    },
    {
      "x": 427.93,
      "y": 865.37,
      "distPct": 0.7427
    },
    {
      "x": 430.57,
      "y": 868.29,
      "distPct": 0.7434
    },
    {
      "x": 433.26,
      "y": 871.26,
      "distPct": 0.7441
    },
    {
      "x": 436.0,
      "y": 874.3,
      "distPct": 0.7449
    },
    {
      "x": 436.0,
      "y": 874.3,
      "distPct": 0.7449
    },
    {
      "x": 466.12,
      "y": 900.34,
      "distPct": 0.7523
    },
    {
      "x": 501.05,
      "y": 919.39,
      "distPct": 0.7597
    },
    {
      "x": 536.8,
      "y": 931.52,
      "distPct": 0.7667
    },
    {
      "x": 569.4,
      "y": 936.8,
      "distPct": 0.7728
    },
    {
      "x": 604.6,
      "y": 938.41,
      "distPct": 0.7794
    },
    {
      "x": 646.11,
      "y": 939.42,
      "distPct": 0.7871
    },
    {
      "x": 691.39,
      "y": 939.95,
      "distPct": 0.7955
    },
    {
      "x": 737.9,
      "y": 940.1,
      "distPct": 0.8042
    },
    {
      "x": 776.46,
      "y": 940.02,
      "distPct": 0.8113
    },
    {
      "x": 812.51,
      "y": 939.8,
      "distPct": 0.818
    },
    {
      "x": 844.54,
      "y": 939.51,
      "distPct": 0.824
    },
    {
      "x": 871.0,
      "y": 939.2,
      "distPct": 0.8289
    },
    {
      "x": 921.35,
      "y": 936.86,
      "distPct": 0.8382
    },
    {
      "x": 957.11,
      "y": 931.36,
      "distPct": 0.845
    },
    {
      "x": 984.27,
      "y": 922.96,
      "distPct": 0.8502
    },
    {
      "x": 1008.8,
      "y": 911.9,
      "distPct": 0.8552
    },
    {
      "x": 1132.17,
      "y": 850.52,
      "distPct": 0.8808
    },
    {
      "x": 1269.72,
      "y": 779.66,
      "distPct": 0.9096
    },
    {
      "x": 1420.97,
      "y": 699.6,
      "distPct": 0.9414
    },
    {
      "x": 1585.4,
      "y": 610.6,
      "distPct": 0.9761
    },
    {
      "x": 1605.09,
      "y": 596.23,
      "distPct": 0.9806
    },
    {
      "x": 1616.53,
      "y": 580.97,
      "distPct": 0.9842
    },
    {
      "x": 1621.85,
      "y": 566.58,
      "distPct": 0.987
    },
    {
      "x": 1623.2,
      "y": 554.8,
      "distPct": 0.9892
    },
    {
      "x": 1621.35,
      "y": 539.76,
      "distPct": 0.992
    },
    {
      "x": 1615.99,
      "y": 526.0,
      "distPct": 0.9948
    },
    {
      "x": 1607.6,
      "y": 514.41,
      "distPct": 0.9974
    },
    {
      "x": 1596.7,
      "y": 505.9,
      "distPct": 1.0
    }
  ],
  "bounds": {
    "xMin": 296.85,
    "xMax": 1623.2,
    "yMin": 140.4,
    "yMax": 940.1
  },
  "pointCount": 197,
  "source": "iTelemetry/iracing-tracks",
  "baseline": 0.919,
  "clockwise": false
}