{
  "name": "Layer 1",
  "trackId": "231",
  "centerline": [
    {
      "x": 1435.2,
      "y": 914.0,
      "distPct": 0
    },
    {
      "x": 1431.82,
      "y": 913.93,
      "distPct": 0.0009
    },
    {
      "x": 1428.6,
      "y": 913.74,
      "distPct": 0.0018
    },
    {
      "x": 1425.61,
      "y": 913.45,
      "distPct": 0.0026
    },
    {
      "x": 1422.9,
      "y": 913.1,
      "distPct": 0.0033
    },
    {
      "x": 1422.17,
      "y": 913.03,
      "distPct": 0.0035
    },
    {
      "x": 1421.49,
      "y": 912.96,
      "distPct": 0.0037
    },
    {
      "x": 1420.86,
      "y": 912.92,
      "distPct": 0.0038
    },
    {
      "x": 1420.3,
      "y": 912.9,
      "distPct": 0.004
    },
    {
      "x": 1369.03,
      "y": 909.02,
      "distPct": 0.0178
    },
    {
      "x": 1315.95,
      "y": 904.49,
      "distPct": 0.032
    },
    {
      "x": 1256.05,
      "y": 898.74,
      "distPct": 0.0481
    },
    {
      "x": 1184.3,
      "y": 891.2,
      "distPct": 0.0674
    },
    {
      "x": 1164.22,
      "y": 887.21,
      "distPct": 0.0729
    },
    {
      "x": 1142.01,
      "y": 866.07,
      "distPct": 0.0813
    },
    {
      "x": 1136.5,
      "y": 845.6,
      "distPct": 0.087
    },
    {
      "x": 1131.44,
      "y": 814.32,
      "distPct": 0.0955
    },
    {
      "x": 1125.8,
      "y": 774.51,
      "distPct": 0.1062
    },
    {
      "x": 1120.38,
      "y": 733.45,
      "distPct": 0.1173
    },
    {
      "x": 1116.0,
      "y": 698.4,
      "distPct": 0.1267
    },
    {
      "x": 1115.8,
      "y": 696.3,
      "distPct": 0.1273
    },
    {
      "x": 1113.48,
      "y": 677.68,
      "distPct": 0.1323
    },
    {
      "x": 1111.33,
      "y": 664.97,
      "distPct": 0.1358
    },
    {
      "x": 1108.68,
      "y": 656.28,
      "distPct": 0.1382
    },
    {
      "x": 1104.9,
      "y": 649.7,
      "distPct": 0.1402
    },
    {
      "x": 1089.17,
      "y": 630.05,
      "distPct": 0.147
    },
    {
      "x": 1076.88,
      "y": 616.6,
      "distPct": 0.1518
    },
    {
      "x": 1054.1,
      "y": 597.0,
      "distPct": 0.1599
    },
    {
      "x": 1042.0,
      "y": 589.44,
      "distPct": 0.1637
    },
    {
      "x": 1030.31,
      "y": 585.12,
      "distPct": 0.167
    },
    {
      "x": 1019.77,
      "y": 583.02,
      "distPct": 0.1699
    },
    {
      "x": 1011.1,
      "y": 582.1,
      "distPct": 0.1722
    },
    {
      "x": 1002.66,
      "y": 581.46,
      "distPct": 0.1745
    },
    {
      "x": 993.2,
      "y": 580.89,
      "distPct": 0.177
    },
    {
      "x": 983.59,
      "y": 580.37,
      "distPct": 0.1796
    },
    {
      "x": 974.7,
      "y": 579.9,
      "distPct": 0.182
    },
    {
      "x": 969.6,
      "y": 579.6,
      "distPct": 0.1834
    },
    {
      "x": 955.82,
      "y": 579.35,
      "distPct": 0.1871
    },
    {
      "x": 945.31,
      "y": 580.54,
      "distPct": 0.1899
    },
    {
      "x": 937.07,
      "y": 583.35,
      "distPct": 0.1922
    },
    {
      "x": 926.08,
      "y": 591.42,
      "distPct": 0.1959
    },
    {
      "x": 920.84,
      "y": 595.95,
      "distPct": 0.1977
    },
    {
      "x": 914.9,
      "y": 601.08,
      "distPct": 0.1998
    },
    {
      "x": 908.8,
      "y": 606.3,
      "distPct": 0.202
    },
    {
      "x": 904.87,
      "y": 609.69,
      "distPct": 0.2034
    },
    {
      "x": 901.26,
      "y": 612.84,
      "distPct": 0.2046
    },
    {
      "x": 898.13,
      "y": 615.6,
      "distPct": 0.2058
    },
    {
      "x": 895.6,
      "y": 617.8,
      "distPct": 0.2066
    },
    {
      "x": 887.38,
      "y": 625.78,
      "distPct": 0.2097
    },
    {
      "x": 882.51,
      "y": 633.49,
      "distPct": 0.2122
    },
    {
      "x": 880.29,
      "y": 642.68,
      "distPct": 0.2147
    },
    {
      "x": 880.0,
      "y": 655.1,
      "distPct": 0.218
    },
    {
      "x": 881.29,
      "y": 689.93,
      "distPct": 0.2273
    },
    {
      "x": 883.12,
      "y": 730.05,
      "distPct": 0.2381
    },
    {
      "x": 887.0,
      "y": 805.3,
      "distPct": 0.2582
    },
    {
      "x": 887.6,
      "y": 817.2,
      "distPct": 0.2614
    },
    {
      "x": 887.32,
      "y": 827.58,
      "distPct": 0.2642
    },
    {
      "x": 885.41,
      "y": 836.37,
      "distPct": 0.2666
    },
    {
      "x": 881.88,
      "y": 843.55,
      "distPct": 0.2687
    },
    {
      "x": 876.7,
      "y": 849.1,
      "distPct": 0.2708
    },
    {
      "x": 868.7,
      "y": 853.25,
      "distPct": 0.2732
    },
    {
      "x": 861.13,
      "y": 854.44,
      "distPct": 0.2752
    },
    {
      "x": 855.24,
      "y": 854.04,
      "distPct": 0.2768
    },
    {
      "x": 852.3,
      "y": 853.4,
      "distPct": 0.2776
    },
    {
      "x": 851.1,
      "y": 853.1,
      "distPct": 0.2779
    },
    {
      "x": 850.0,
      "y": 852.5,
      "distPct": 0.2783
    },
    {
      "x": 846.19,
      "y": 850.29,
      "distPct": 0.2795
    },
    {
      "x": 828.48,
      "y": 839.52,
      "distPct": 0.285
    },
    {
      "x": 820.4,
      "y": 834.1,
      "distPct": 0.2876
    },
    {
      "x": 814.18,
      "y": 829.04,
      "distPct": 0.2898
    },
    {
      "x": 809.35,
      "y": 824.02,
      "distPct": 0.2916
    },
    {
      "x": 805.49,
      "y": 818.52,
      "distPct": 0.2934
    },
    {
      "x": 802.2,
      "y": 812.0,
      "distPct": 0.2954
    },
    {
      "x": 799.04,
      "y": 803.11,
      "distPct": 0.2979
    },
    {
      "x": 795.95,
      "y": 791.89,
      "distPct": 0.301
    },
    {
      "x": 793.31,
      "y": 780.8,
      "distPct": 0.3041
    },
    {
      "x": 791.5,
      "y": 772.3,
      "distPct": 0.3064
    },
    {
      "x": 788.97,
      "y": 755.53,
      "distPct": 0.3109
    },
    {
      "x": 788.3,
      "y": 740.61,
      "distPct": 0.3149
    },
    {
      "x": 789.5,
      "y": 727.29,
      "distPct": 0.3185
    },
    {
      "x": 792.47,
      "y": 703.18,
      "distPct": 0.325
    },
    {
      "x": 786.54,
      "y": 692.05,
      "distPct": 0.3284
    },
    {
      "x": 779.09,
      "y": 683.55,
      "distPct": 0.3314
    },
    {
      "x": 774.4,
      "y": 679.3,
      "distPct": 0.3331
    },
    {
      "x": 767.98,
      "y": 674.44,
      "distPct": 0.3353
    },
    {
      "x": 760.46,
      "y": 669.29,
      "distPct": 0.3377
    },
    {
      "x": 752.59,
      "y": 664.49,
      "distPct": 0.3402
    },
    {
      "x": 745.1,
      "y": 660.7,
      "distPct": 0.3424
    },
    {
      "x": 742.37,
      "y": 659.61,
      "distPct": 0.3432
    },
    {
      "x": 739.19,
      "y": 658.72,
      "distPct": 0.3441
    },
    {
      "x": 736.06,
      "y": 658.48,
      "distPct": 0.3449
    },
    {
      "x": 733.5,
      "y": 659.3,
      "distPct": 0.3457
    },
    {
      "x": 730.26,
      "y": 664.29,
      "distPct": 0.3473
    },
    {
      "x": 728.24,
      "y": 672.41,
      "distPct": 0.3495
    },
    {
      "x": 728.0,
      "y": 692.2,
      "distPct": 0.3548
    },
    {
      "x": 729.37,
      "y": 704.07,
      "distPct": 0.358
    },
    {
      "x": 730.66,
      "y": 715.2,
      "distPct": 0.361
    },
    {
      "x": 731.9,
      "y": 725.72,
      "distPct": 0.3638
    },
    {
      "x": 733.1,
      "y": 735.8,
      "distPct": 0.3665
    },
    {
      "x": 736.0,
      "y": 760.66,
      "distPct": 0.3732
    },
    {
      "x": 738.93,
      "y": 785.3,
      "distPct": 0.3799
    },
    {
      "x": 742.18,
      "y": 812.19,
      "distPct": 0.3871
    },
    {
      "x": 746.1,
      "y": 843.8,
      "distPct": 0.3956
    },
    {
      "x": 746.74,
      "y": 854.84,
      "distPct": 0.3986
    },
    {
      "x": 745.64,
      "y": 863.84,
      "distPct": 0.401
    },
    {
      "x": 742.8,
      "y": 870.87,
      "distPct": 0.4031
    },
    {
      "x": 738.2,
      "y": 876.0,
      "distPct": 0.4049
    },
    {
      "x": 729.46,
      "y": 879.46,
      "distPct": 0.4074
    },
    {
      "x": 724.57,
      "y": 879.3,
      "distPct": 0.4088
    },
    {
      "x": 719.6,
      "y": 877.9,
      "distPct": 0.4101
    },
    {
      "x": 688.01,
      "y": 865.86,
      "distPct": 0.4192
    },
    {
      "x": 619.26,
      "y": 839.35,
      "distPct": 0.4389
    },
    {
      "x": 539.36,
      "y": 807.81,
      "distPct": 0.4619
    },
    {
      "x": 474.3,
      "y": 780.7,
      "distPct": 0.4807
    },
    {
      "x": 463.04,
      "y": 772.03,
      "distPct": 0.4845
    },
    {
      "x": 459.0,
      "y": 760.71,
      "distPct": 0.4877
    },
    {
      "x": 459.98,
      "y": 748.06,
      "distPct": 0.4911
    },
    {
      "x": 463.8,
      "y": 735.4,
      "distPct": 0.4947
    },
    {
      "x": 464.74,
      "y": 732.56,
      "distPct": 0.4955
    },
    {
      "x": 465.94,
      "y": 728.51,
      "distPct": 0.4966
    },
    {
      "x": 468.3,
      "y": 720.2,
      "distPct": 0.4989
    },
    {
      "x": 468.5,
      "y": 719.5,
      "distPct": 0.4991
    },
    {
      "x": 468.96,
      "y": 717.84,
      "distPct": 0.4996
    },
    {
      "x": 469.26,
      "y": 716.02,
      "distPct": 0.5001
    },
    {
      "x": 469.36,
      "y": 714.32,
      "distPct": 0.5005
    },
    {
      "x": 469.2,
      "y": 713.0,
      "distPct": 0.5009
    },
    {
      "x": 463.8,
      "y": 710.75,
      "distPct": 0.5024
    },
    {
      "x": 458.6,
      "y": 705.61,
      "distPct": 0.5044
    },
    {
      "x": 455.28,
      "y": 696.45,
      "distPct": 0.507
    },
    {
      "x": 455.5,
      "y": 682.1,
      "distPct": 0.5108
    },
    {
      "x": 458.07,
      "y": 666.37,
      "distPct": 0.5151
    },
    {
      "x": 461.44,
      "y": 647.75,
      "distPct": 0.5202
    },
    {
      "x": 464.94,
      "y": 629.28,
      "distPct": 0.5252
    },
    {
      "x": 467.9,
      "y": 614.0,
      "distPct": 0.5294
    },
    {
      "x": 468.25,
      "y": 611.79,
      "distPct": 0.53
    },
    {
      "x": 468.43,
      "y": 610.53,
      "distPct": 0.5303
    },
    {
      "x": 468.6,
      "y": 609.2,
      "distPct": 0.5307
    },
    {
      "x": 469.83,
      "y": 601.65,
      "distPct": 0.5327
    },
    {
      "x": 471.84,
      "y": 593.72,
      "distPct": 0.5349
    },
    {
      "x": 475.25,
      "y": 586.36,
      "distPct": 0.5371
    },
    {
      "x": 480.7,
      "y": 580.5,
      "distPct": 0.5392
    },
    {
      "x": 484.01,
      "y": 578.59,
      "distPct": 0.5402
    },
    {
      "x": 487.6,
      "y": 577.4,
      "distPct": 0.5412
    },
    {
      "x": 491.42,
      "y": 576.96,
      "distPct": 0.5423
    },
    {
      "x": 495.4,
      "y": 577.3,
      "distPct": 0.5433
    },
    {
      "x": 531.1,
      "y": 575.42,
      "distPct": 0.5529
    },
    {
      "x": 558.41,
      "y": 561.72,
      "distPct": 0.5611
    },
    {
      "x": 586.1,
      "y": 532.5,
      "distPct": 0.5719
    },
    {
      "x": 609.3,
      "y": 503.56,
      "distPct": 0.5818
    },
    {
      "x": 630.56,
      "y": 489.17,
      "distPct": 0.5887
    },
    {
      "x": 650.27,
      "y": 485.02,
      "distPct": 0.5941
    },
    {
      "x": 668.8,
      "y": 486.8,
      "distPct": 0.599
    },
    {
      "x": 699.41,
      "y": 489.3,
      "distPct": 0.6072
    },
    {
      "x": 721.81,
      "y": 485.05,
      "distPct": 0.6133
    },
    {
      "x": 738.09,
      "y": 476.0,
      "distPct": 0.6183
    },
    {
      "x": 750.3,
      "y": 464.1,
      "distPct": 0.6229
    },
    {
      "x": 772.69,
      "y": 442.95,
      "distPct": 0.6311
    },
    {
      "x": 793.41,
      "y": 431.75,
      "distPct": 0.6374
    },
    {
      "x": 812.13,
      "y": 427.23,
      "distPct": 0.6426
    },
    {
      "x": 828.5,
      "y": 426.1,
      "distPct": 0.647
    },
    {
      "x": 901.5,
      "y": 422.75,
      "distPct": 0.6665
    },
    {
      "x": 941.56,
      "y": 420.59,
      "distPct": 0.6773
    },
    {
      "x": 974.8,
      "y": 418.5,
      "distPct": 0.6862
    },
    {
      "x": 1018.85,
      "y": 409.35,
      "distPct": 0.6982
    },
    {
      "x": 1046.83,
      "y": 391.31,
      "distPct": 0.7071
    },
    {
      "x": 1063.37,
      "y": 367.3,
      "distPct": 0.7149
    },
    {
      "x": 1073.1,
      "y": 340.2,
      "distPct": 0.7226
    },
    {
      "x": 1076.99,
      "y": 324.04,
      "distPct": 0.7271
    },
    {
      "x": 1080.61,
      "y": 304.59,
      "distPct": 0.7323
    },
    {
      "x": 1084.03,
      "y": 283.09,
      "distPct": 0.7382
    },
    {
      "x": 1087.3,
      "y": 260.8,
      "distPct": 0.7442
    },
    {
      "x": 1090.17,
      "y": 241.67,
      "distPct": 0.7494
    },
    {
      "x": 1092.99,
      "y": 223.67,
      "distPct": 0.7542
    },
    {
      "x": 1095.86,
      "y": 207.45,
      "distPct": 0.7587
    },
    {
      "x": 1102.68,
      "y": 182.5,
      "distPct": 0.7656
    },
    {
      "x": 1107.71,
      "y": 174.27,
      "distPct": 0.7682
    },
    {
      "x": 1113.96,
      "y": 168.93,
      "distPct": 0.7704
    },
    {
      "x": 1121.4,
      "y": 166.5,
      "distPct": 0.7725
    },
    {
      "x": 1134.19,
      "y": 169.09,
      "distPct": 0.7759
    },
    {
      "x": 1144.19,
      "y": 176.84,
      "distPct": 0.7793
    },
    {
      "x": 1150.72,
      "y": 185.02,
      "distPct": 0.7821
    },
    {
      "x": 1153.1,
      "y": 188.9,
      "distPct": 0.7833
    },
    {
      "x": 1159.2,
      "y": 200.77,
      "distPct": 0.7869
    },
    {
      "x": 1166.36,
      "y": 215.04,
      "distPct": 0.7912
    },
    {
      "x": 1173.39,
      "y": 229.36,
      "distPct": 0.7955
    },
    {
      "x": 1179.1,
      "y": 241.4,
      "distPct": 0.799
    },
    {
      "x": 1226.3,
      "y": 346.05,
      "distPct": 0.8297
    },
    {
      "x": 1341.76,
      "y": 606.34,
      "distPct": 0.9059
    },
    {
      "x": 1399.7,
      "y": 737.7,
      "distPct": 0.9443
    },
    {
      "x": 1416.05,
      "y": 774.73,
      "distPct": 0.9551
    },
    {
      "x": 1431.65,
      "y": 810.11,
      "distPct": 0.9655
    },
    {
      "x": 1446.28,
      "y": 843.27,
      "distPct": 0.9752
    },
    {
      "x": 1459.7,
      "y": 873.6,
      "distPct": 0.984
    },
    {
      "x": 1462.91,
      "y": 882.73,
      "distPct": 0.9866
    },
    {
      "x": 1463.99,
      "y": 890.9,
      "distPct": 0.9888
    },
    {
      "x": 1462.95,
      "y": 898.1,
      "distPct": 0.9908
    },
    {
      "x": 1459.8,
      "y": 904.3,
      "distPct": 0.9926
    },
    {
      "x": 1455.0,
      "y": 909.15,
      "distPct": 0.9945
    },
    {
      "x": 1448.93,
      "y": 912.11,
      "distPct": 0.9963
    },
    {
      "x": 1442.14,
      "y": 913.6,
      "distPct": 0.9981
    }
  ],
  "bounds": {
    "xMin": 455.28,
    "xMax": 1463.99,
    "yMin": 166.5,
    "yMax": 914.0
  },
  "pointCount": 200,
  "source": "iTelemetry/iracing-tracks",
  "baseline": 0.125,
  "clockwise": true
}