{
  "name": "Oval - Config",
  "trackId": "447",
  "centerline": [
    {
      "x": 1179.4,
      "y": 951.0,
      "distPct": 0
    },
    {
      "x": 762.0,
      "y": 949.4,
      "distPct": 0.108
    },
    {
      "x": 761.2,
      "y": 949.2,
      "distPct": 0.1082
    },
    {
      "x": 749.29,
      "y": 946.7,
      "distPct": 0.1114
    },
    {
      "x": 717.18,
      "y": 939.14,
      "distPct": 0.1199
    },
    {
      "x": 668.89,
      "y": 926.24,
      "distPct": 0.1329
    },
    {
      "x": 608.5,
      "y": 907.7,
      "distPct": 0.1492
    },
    {
      "x": 542.56,
      "y": 884.22,
      "distPct": 0.1673
    },
    {
      "x": 468.53,
      "y": 853.21,
      "distPct": 0.1881
    },
    {
      "x": 391.6,
      "y": 814.42,
      "distPct": 0.2104
    },
    {
      "x": 317.0,
      "y": 767.6,
      "distPct": 0.2332
    },
    {
      "x": 302.82,
      "y": 754.86,
      "distPct": 0.2381
    },
    {
      "x": 284.46,
      "y": 733.42,
      "distPct": 0.2455
    },
    {
      "x": 264.03,
      "y": 703.92,
      "distPct": 0.2547
    },
    {
      "x": 243.6,
      "y": 667.0,
      "distPct": 0.2657
    },
    {
      "x": 227.37,
      "y": 628.65,
      "distPct": 0.2764
    },
    {
      "x": 213.83,
      "y": 582.01,
      "distPct": 0.289
    },
    {
      "x": 206.39,
      "y": 528.5,
      "distPct": 0.303
    },
    {
      "x": 208.5,
      "y": 469.5,
      "distPct": 0.3183
    },
    {
      "x": 219.62,
      "y": 413.65,
      "distPct": 0.333
    },
    {
      "x": 237.79,
      "y": 362.01,
      "distPct": 0.3472
    },
    {
      "x": 262.91,
      "y": 314.74,
      "distPct": 0.361
    },
    {
      "x": 294.9,
      "y": 272.0,
      "distPct": 0.3749
    },
    {
      "x": 335.18,
      "y": 232.89,
      "distPct": 0.3894
    },
    {
      "x": 381.98,
      "y": 199.91,
      "distPct": 0.4042
    },
    {
      "x": 435.1,
      "y": 173.18,
      "distPct": 0.4196
    },
    {
      "x": 494.4,
      "y": 152.8,
      "distPct": 0.4358
    },
    {
      "x": 494.7,
      "y": 152.7,
      "distPct": 0.4359
    },
    {
      "x": 534.25,
      "y": 144.06,
      "distPct": 0.4464
    },
    {
      "x": 578.46,
      "y": 136.46,
      "distPct": 0.458
    },
    {
      "x": 621.64,
      "y": 131.06,
      "distPct": 0.4693
    },
    {
      "x": 658.1,
      "y": 129.0,
      "distPct": 0.4787
    },
    {
      "x": 778.29,
      "y": 129.89,
      "distPct": 0.5098
    },
    {
      "x": 1005.05,
      "y": 131.85,
      "distPct": 0.5685
    },
    {
      "x": 1225.66,
      "y": 133.81,
      "distPct": 0.6256
    },
    {
      "x": 1327.4,
      "y": 134.7,
      "distPct": 0.652
    },
    {
      "x": 1351.49,
      "y": 137.7,
      "distPct": 0.6582
    },
    {
      "x": 1404.33,
      "y": 147.64,
      "distPct": 0.6722
    },
    {
      "x": 1468.9,
      "y": 167.09,
      "distPct": 0.6896
    },
    {
      "x": 1528.2,
      "y": 198.6,
      "distPct": 0.707
    },
    {
      "x": 1530.69,
      "y": 200.48,
      "distPct": 0.7078
    },
    {
      "x": 1533.21,
      "y": 202.36,
      "distPct": 0.7086
    },
    {
      "x": 1535.75,
      "y": 204.27,
      "distPct": 0.7094
    },
    {
      "x": 1538.3,
      "y": 206.2,
      "distPct": 0.7103
    },
    {
      "x": 1565.5,
      "y": 226.85,
      "distPct": 0.7191
    },
    {
      "x": 1594.35,
      "y": 250.96,
      "distPct": 0.7288
    },
    {
      "x": 1623.35,
      "y": 279.59,
      "distPct": 0.7394
    },
    {
      "x": 1651.0,
      "y": 313.8,
      "distPct": 0.7508
    },
    {
      "x": 1678.36,
      "y": 359.99,
      "distPct": 0.7647
    },
    {
      "x": 1697.95,
      "y": 410.44,
      "distPct": 0.7787
    },
    {
      "x": 1709.89,
      "y": 465.52,
      "distPct": 0.7933
    },
    {
      "x": 1714.3,
      "y": 525.6,
      "distPct": 0.8088
    },
    {
      "x": 1714.01,
      "y": 537.55,
      "distPct": 0.8119
    },
    {
      "x": 1710.88,
      "y": 565.54,
      "distPct": 0.8192
    },
    {
      "x": 1701.7,
      "y": 605.88,
      "distPct": 0.8299
    },
    {
      "x": 1683.3,
      "y": 654.9,
      "distPct": 0.8435
    },
    {
      "x": 1667.4,
      "y": 685.38,
      "distPct": 0.8524
    },
    {
      "x": 1648.76,
      "y": 714.15,
      "distPct": 0.8613
    },
    {
      "x": 1627.51,
      "y": 741.05,
      "distPct": 0.8701
    },
    {
      "x": 1603.8,
      "y": 765.9,
      "distPct": 0.879
    },
    {
      "x": 1570.2,
      "y": 794.76,
      "distPct": 0.8905
    },
    {
      "x": 1532.62,
      "y": 820.69,
      "distPct": 0.9023
    },
    {
      "x": 1491.19,
      "y": 843.6,
      "distPct": 0.9146
    },
    {
      "x": 1446.0,
      "y": 863.4,
      "distPct": 0.9273
    },
    {
      "x": 1445.8,
      "y": 863.5,
      "distPct": 0.9274
    },
    {
      "x": 1391.13,
      "y": 883.25,
      "distPct": 0.9424
    },
    {
      "x": 1314.49,
      "y": 910.01,
      "distPct": 0.9634
    },
    {
      "x": 1236.93,
      "y": 935.37,
      "distPct": 0.9846
    },
    {
      "x": 1179.5,
      "y": 950.9,
      "distPct": 1.0
    },
    {
      "x": 1179.4,
      "y": 951.0,
      "distPct": 1.0
    }
  ],
  "bounds": {
    "xMin": 206.39,
    "xMax": 1714.3,
    "yMin": 129.0,
    "yMax": 951.0
  },
  "pointCount": 70,
  "source": "iTelemetry/iracing-tracks",
  "baseline": 0.943,
  "clockwise": true
}