{
  "name": "Barber Full Config",
  "trackId": "46",
  "centerline": [
    {
      "x": 1662.5,
      "y": 928.8,
      "distPct": 0
    },
    {
      "x": 1654.34,
      "y": 928.67,
      "distPct": 0.0012
    },
    {
      "x": 1646.22,
      "y": 928.12,
      "distPct": 0.0025
    },
    {
      "x": 1638.14,
      "y": 927.17,
      "distPct": 0.0037
    },
    {
      "x": 1630.1,
      "y": 925.8,
      "distPct": 0.005
    },
    {
      "x": 1612.18,
      "y": 920.74,
      "distPct": 0.0078
    },
    {
      "x": 1596.88,
      "y": 913.4,
      "distPct": 0.0104
    },
    {
      "x": 1584.23,
      "y": 903.81,
      "distPct": 0.0128
    },
    {
      "x": 1574.3,
      "y": 892.0,
      "distPct": 0.0152
    },
    {
      "x": 1569.12,
      "y": 882.71,
      "distPct": 0.0168
    },
    {
      "x": 1565.3,
      "y": 872.48,
      "distPct": 0.0185
    },
    {
      "x": 1562.82,
      "y": 861.23,
      "distPct": 0.0202
    },
    {
      "x": 1561.7,
      "y": 848.9,
      "distPct": 0.0221
    },
    {
      "x": 1561.32,
      "y": 824.81,
      "distPct": 0.0258
    },
    {
      "x": 1561.62,
      "y": 795.12,
      "distPct": 0.0303
    },
    {
      "x": 1562.35,
      "y": 765.03,
      "distPct": 0.0349
    },
    {
      "x": 1563.2,
      "y": 739.7,
      "distPct": 0.0388
    },
    {
      "x": 1562.03,
      "y": 713.62,
      "distPct": 0.0428
    },
    {
      "x": 1556.78,
      "y": 689.44,
      "distPct": 0.0466
    },
    {
      "x": 1547.73,
      "y": 668.16,
      "distPct": 0.0501
    },
    {
      "x": 1535.2,
      "y": 650.8,
      "distPct": 0.0534
    },
    {
      "x": 1525.74,
      "y": 642.35,
      "distPct": 0.0553
    },
    {
      "x": 1515.39,
      "y": 636.21,
      "distPct": 0.0571
    },
    {
      "x": 1504.19,
      "y": 632.42,
      "distPct": 0.059
    },
    {
      "x": 1492.2,
      "y": 631.0,
      "distPct": 0.0608
    },
    {
      "x": 1334.9,
      "y": 628.53,
      "distPct": 0.0848
    },
    {
      "x": 1147.55,
      "y": 627.06,
      "distPct": 0.1134
    },
    {
      "x": 950.82,
      "y": 626.29,
      "distPct": 0.1435
    },
    {
      "x": 765.4,
      "y": 625.9,
      "distPct": 0.1718
    },
    {
      "x": 729.39,
      "y": 625.82,
      "distPct": 0.1773
    },
    {
      "x": 694.98,
      "y": 625.75,
      "distPct": 0.1825
    },
    {
      "x": 662.32,
      "y": 625.67,
      "distPct": 0.1875
    },
    {
      "x": 631.6,
      "y": 625.6,
      "distPct": 0.1922
    },
    {
      "x": 598.22,
      "y": 630.09,
      "distPct": 0.1973
    },
    {
      "x": 574.7,
      "y": 642.06,
      "distPct": 0.2014
    },
    {
      "x": 558.53,
      "y": 659.31,
      "distPct": 0.205
    },
    {
      "x": 547.2,
      "y": 679.6,
      "distPct": 0.2085
    },
    {
      "x": 544.68,
      "y": 685.13,
      "distPct": 0.2095
    },
    {
      "x": 541.94,
      "y": 691.16,
      "distPct": 0.2105
    },
    {
      "x": 539.03,
      "y": 697.59,
      "distPct": 0.2116
    },
    {
      "x": 536.0,
      "y": 704.3,
      "distPct": 0.2127
    },
    {
      "x": 519.82,
      "y": 739.81,
      "distPct": 0.2186
    },
    {
      "x": 502.04,
      "y": 777.23,
      "distPct": 0.225
    },
    {
      "x": 483.79,
      "y": 812.36,
      "distPct": 0.231
    },
    {
      "x": 466.2,
      "y": 841.0,
      "distPct": 0.2361
    },
    {
      "x": 442.72,
      "y": 867.82,
      "distPct": 0.2416
    },
    {
      "x": 419.08,
      "y": 884.24,
      "distPct": 0.246
    },
    {
      "x": 395.92,
      "y": 892.99,
      "distPct": 0.2498
    },
    {
      "x": 373.9,
      "y": 896.8,
      "distPct": 0.2532
    },
    {
      "x": 370.53,
      "y": 897.12,
      "distPct": 0.2537
    },
    {
      "x": 367.15,
      "y": 897.34,
      "distPct": 0.2542
    },
    {
      "x": 363.78,
      "y": 897.46,
      "distPct": 0.2547
    },
    {
      "x": 360.4,
      "y": 897.5,
      "distPct": 0.2552
    },
    {
      "x": 335.19,
      "y": 894.9,
      "distPct": 0.2591
    },
    {
      "x": 313.58,
      "y": 888.14,
      "distPct": 0.2626
    },
    {
      "x": 295.6,
      "y": 878.81,
      "distPct": 0.2656
    },
    {
      "x": 281.3,
      "y": 868.5,
      "distPct": 0.2683
    },
    {
      "x": 266.3,
      "y": 853.97,
      "distPct": 0.2715
    },
    {
      "x": 253.95,
      "y": 837.67,
      "distPct": 0.2747
    },
    {
      "x": 244.82,
      "y": 820.52,
      "distPct": 0.2776
    },
    {
      "x": 239.5,
      "y": 803.4,
      "distPct": 0.2804
    },
    {
      "x": 238.25,
      "y": 752.96,
      "distPct": 0.2881
    },
    {
      "x": 251.14,
      "y": 714.61,
      "distPct": 0.2942
    },
    {
      "x": 270.31,
      "y": 687.23,
      "distPct": 0.2993
    },
    {
      "x": 287.9,
      "y": 669.7,
      "distPct": 0.3031
    },
    {
      "x": 312.14,
      "y": 648.36,
      "distPct": 0.3081
    },
    {
      "x": 343.38,
      "y": 622.33,
      "distPct": 0.3143
    },
    {
      "x": 375.85,
      "y": 596.63,
      "distPct": 0.3206
    },
    {
      "x": 403.8,
      "y": 576.3,
      "distPct": 0.3259
    },
    {
      "x": 449.05,
      "y": 550.24,
      "distPct": 0.3338
    },
    {
      "x": 485.66,
      "y": 537.0,
      "distPct": 0.3398
    },
    {
      "x": 516.37,
      "y": 532.31,
      "distPct": 0.3445
    },
    {
      "x": 543.9,
      "y": 531.9,
      "distPct": 0.3487
    },
    {
      "x": 612.8,
      "y": 531.85,
      "distPct": 0.3593
    },
    {
      "x": 692.55,
      "y": 531.11,
      "distPct": 0.3714
    },
    {
      "x": 779.05,
      "y": 529.95,
      "distPct": 0.3846
    },
    {
      "x": 868.2,
      "y": 528.6,
      "distPct": 0.3983
    },
    {
      "x": 939.5,
      "y": 527.48,
      "distPct": 0.4091
    },
    {
      "x": 1009.5,
      "y": 526.46,
      "distPct": 0.4198
    },
    {
      "x": 1075.68,
      "y": 525.69,
      "distPct": 0.4299
    },
    {
      "x": 1135.5,
      "y": 525.3,
      "distPct": 0.4391
    },
    {
      "x": 1149.99,
      "y": 524.36,
      "distPct": 0.4413
    },
    {
      "x": 1162.08,
      "y": 521.71,
      "distPct": 0.4432
    },
    {
      "x": 1171.72,
      "y": 517.35,
      "distPct": 0.4448
    },
    {
      "x": 1178.9,
      "y": 511.3,
      "distPct": 0.4462
    },
    {
      "x": 1170.15,
      "y": 481.6,
      "distPct": 0.451
    },
    {
      "x": 1156.64,
      "y": 461.88,
      "distPct": 0.4546
    },
    {
      "x": 1140.86,
      "y": 449.76,
      "distPct": 0.4576
    },
    {
      "x": 1125.3,
      "y": 442.9,
      "distPct": 0.4602
    },
    {
      "x": 1097.11,
      "y": 434.69,
      "distPct": 0.4647
    },
    {
      "x": 1064.09,
      "y": 427.04,
      "distPct": 0.4699
    },
    {
      "x": 1030.22,
      "y": 420.19,
      "distPct": 0.4752
    },
    {
      "x": 999.5,
      "y": 414.4,
      "distPct": 0.48
    },
    {
      "x": 994.67,
      "y": 413.52,
      "distPct": 0.4807
    },
    {
      "x": 990.08,
      "y": 412.68,
      "distPct": 0.4814
    },
    {
      "x": 985.75,
      "y": 411.87,
      "distPct": 0.4821
    },
    {
      "x": 981.7,
      "y": 411.1,
      "distPct": 0.4827
    },
    {
      "x": 938.52,
      "y": 405.48,
      "distPct": 0.4894
    },
    {
      "x": 900.41,
      "y": 405.1,
      "distPct": 0.4952
    },
    {
      "x": 866.82,
      "y": 408.4,
      "distPct": 0.5003
    },
    {
      "x": 837.2,
      "y": 413.8,
      "distPct": 0.5049
    },
    {
      "x": 790.33,
      "y": 423.32,
      "distPct": 0.5122
    },
    {
      "x": 735.31,
      "y": 433.78,
      "distPct": 0.5208
    },
    {
      "x": 675.21,
      "y": 444.79,
      "distPct": 0.5301
    },
    {
      "x": 613.1,
      "y": 456.0,
      "distPct": 0.5398
    },
    {
      "x": 554.64,
      "y": 466.53,
      "distPct": 0.5488
    },
    {
      "x": 498.01,
      "y": 476.9,
      "distPct": 0.5576
    },
    {
      "x": 446.05,
      "y": 486.74,
      "distPct": 0.5657
    },
    {
      "x": 401.6,
      "y": 495.7,
      "distPct": 0.5726
    },
    {
      "x": 396.9,
      "y": 496.7,
      "distPct": 0.5733
    },
    {
      "x": 364.24,
      "y": 503.52,
      "distPct": 0.5784
    },
    {
      "x": 325.6,
      "y": 511.24,
      "distPct": 0.5845
    },
    {
      "x": 286.96,
      "y": 518.26,
      "distPct": 0.5905
    },
    {
      "x": 254.3,
      "y": 523.0,
      "distPct": 0.5955
    },
    {
      "x": 229.2,
      "y": 523.84,
      "distPct": 0.5993
    },
    {
      "x": 209.99,
      "y": 521.06,
      "distPct": 0.6023
    },
    {
      "x": 195.56,
      "y": 515.98,
      "distPct": 0.6046
    },
    {
      "x": 184.8,
      "y": 509.9,
      "distPct": 0.6065
    },
    {
      "x": 170.73,
      "y": 498.89,
      "distPct": 0.6092
    },
    {
      "x": 159.08,
      "y": 486.81,
      "distPct": 0.6118
    },
    {
      "x": 149.33,
      "y": 474.31,
      "distPct": 0.6142
    },
    {
      "x": 141.0,
      "y": 462.0,
      "distPct": 0.6165
    },
    {
      "x": 132.04,
      "y": 451.87,
      "distPct": 0.6186
    },
    {
      "x": 122.19,
      "y": 446.28,
      "distPct": 0.6203
    },
    {
      "x": 111.79,
      "y": 443.72,
      "distPct": 0.6219
    },
    {
      "x": 101.2,
      "y": 442.7,
      "distPct": 0.6235
    },
    {
      "x": 95.94,
      "y": 442.29,
      "distPct": 0.6244
    },
    {
      "x": 90.86,
      "y": 441.68,
      "distPct": 0.6251
    },
    {
      "x": 86.03,
      "y": 440.65,
      "distPct": 0.6259
    },
    {
      "x": 81.5,
      "y": 439.0,
      "distPct": 0.6266
    },
    {
      "x": 70.14,
      "y": 432.31,
      "distPct": 0.6286
    },
    {
      "x": 61.01,
      "y": 423.88,
      "distPct": 0.6305
    },
    {
      "x": 54.23,
      "y": 413.83,
      "distPct": 0.6324
    },
    {
      "x": 49.9,
      "y": 402.3,
      "distPct": 0.6343
    },
    {
      "x": 48.22,
      "y": 382.43,
      "distPct": 0.6373
    },
    {
      "x": 51.6,
      "y": 363.29,
      "distPct": 0.6403
    },
    {
      "x": 58.06,
      "y": 346.6,
      "distPct": 0.643
    },
    {
      "x": 65.6,
      "y": 334.1,
      "distPct": 0.6452
    },
    {
      "x": 94.94,
      "y": 305.77,
      "distPct": 0.6515
    },
    {
      "x": 126.68,
      "y": 290.21,
      "distPct": 0.6569
    },
    {
      "x": 158.08,
      "y": 283.83,
      "distPct": 0.6618
    },
    {
      "x": 186.4,
      "y": 283.0,
      "distPct": 0.6661
    },
    {
      "x": 245.0,
      "y": 284.22,
      "distPct": 0.675
    },
    {
      "x": 314.4,
      "y": 284.99,
      "distPct": 0.6856
    },
    {
      "x": 389.35,
      "y": 285.43,
      "distPct": 0.6971
    },
    {
      "x": 464.6,
      "y": 285.7,
      "distPct": 0.7086
    },
    {
      "x": 510.04,
      "y": 285.85,
      "distPct": 0.7155
    },
    {
      "x": 553.09,
      "y": 286.04,
      "distPct": 0.7221
    },
    {
      "x": 592.67,
      "y": 286.28,
      "distPct": 0.7281
    },
    {
      "x": 627.7,
      "y": 286.6,
      "distPct": 0.7335
    },
    {
      "x": 644.25,
      "y": 285.91,
      "distPct": 0.736
    },
    {
      "x": 657.31,
      "y": 283.74,
      "distPct": 0.738
    },
    {
      "x": 667.62,
      "y": 280.57,
      "distPct": 0.7397
    },
    {
      "x": 675.9,
      "y": 276.9,
      "distPct": 0.741
    },
    {
      "x": 678.5,
      "y": 274.9,
      "distPct": 0.7415
    },
    {
      "x": 720.95,
      "y": 252.39,
      "distPct": 0.7489
    },
    {
      "x": 758.59,
      "y": 245.19,
      "distPct": 0.7547
    },
    {
      "x": 788.93,
      "y": 247.49,
      "distPct": 0.7594
    },
    {
      "x": 809.5,
      "y": 253.5,
      "distPct": 0.7627
    },
    {
      "x": 949.82,
      "y": 307.54,
      "distPct": 0.7856
    },
    {
      "x": 1117.03,
      "y": 370.23,
      "distPct": 0.8129
    },
    {
      "x": 1290.94,
      "y": 434.37,
      "distPct": 0.8412
    },
    {
      "x": 1451.4,
      "y": 492.8,
      "distPct": 0.8673
    },
    {
      "x": 1464.06,
      "y": 496.46,
      "distPct": 0.8693
    },
    {
      "x": 1474.44,
      "y": 497.54,
      "distPct": 0.8709
    },
    {
      "x": 1483.45,
      "y": 496.5,
      "distPct": 0.8722
    },
    {
      "x": 1492.0,
      "y": 493.8,
      "distPct": 0.8736
    },
    {
      "x": 1514.82,
      "y": 485.34,
      "distPct": 0.8773
    },
    {
      "x": 1544.61,
      "y": 475.34,
      "distPct": 0.8821
    },
    {
      "x": 1574.87,
      "y": 466.59,
      "distPct": 0.8869
    },
    {
      "x": 1599.1,
      "y": 461.9,
      "distPct": 0.8907
    },
    {
      "x": 1623.2,
      "y": 461.22,
      "distPct": 0.8944
    },
    {
      "x": 1645.17,
      "y": 463.69,
      "distPct": 0.8978
    },
    {
      "x": 1664.94,
      "y": 469.28,
      "distPct": 0.9009
    },
    {
      "x": 1682.4,
      "y": 478.0,
      "distPct": 0.9039
    },
    {
      "x": 1695.35,
      "y": 487.76,
      "distPct": 0.9064
    },
    {
      "x": 1705.7,
      "y": 498.41,
      "distPct": 0.9086
    },
    {
      "x": 1713.87,
      "y": 509.23,
      "distPct": 0.9107
    },
    {
      "x": 1720.3,
      "y": 519.5,
      "distPct": 0.9125
    },
    {
      "x": 1749.42,
      "y": 570.25,
      "distPct": 0.9215
    },
    {
      "x": 1785.16,
      "y": 633.45,
      "distPct": 0.9326
    },
    {
      "x": 1815.6,
      "y": 687.58,
      "distPct": 0.942
    },
    {
      "x": 1828.8,
      "y": 711.1,
      "distPct": 0.9462
    },
    {
      "x": 1842.43,
      "y": 744.77,
      "distPct": 0.9517
    },
    {
      "x": 1846.44,
      "y": 779.89,
      "distPct": 0.9571
    },
    {
      "x": 1840.82,
      "y": 815.96,
      "distPct": 0.9627
    },
    {
      "x": 1825.6,
      "y": 852.5,
      "distPct": 0.9687
    },
    {
      "x": 1808.08,
      "y": 879.6,
      "distPct": 0.9737
    },
    {
      "x": 1788.3,
      "y": 903.06,
      "distPct": 0.9783
    },
    {
      "x": 1768.37,
      "y": 922.12,
      "distPct": 0.9826
    },
    {
      "x": 1750.4,
      "y": 936.0,
      "distPct": 0.986
    },
    {
      "x": 1741.46,
      "y": 927.32,
      "distPct": 0.9879
    },
    {
      "x": 1720.14,
      "y": 925.69,
      "distPct": 0.9912
    },
    {
      "x": 1691.97,
      "y": 927.41,
      "distPct": 0.9955
    },
    {
      "x": 1662.5,
      "y": 928.8,
      "distPct": 1.0
    }
  ],
  "bounds": {
    "xMin": 48.22,
    "xMax": 1846.44,
    "yMin": 245.19,
    "yMax": 936.0
  },
  "pointCount": 195,
  "source": "iTelemetry/iracing-tracks",
  "baseline": 0.14400000000000002,
  "clockwise": false
}