{
  "name": "Oval - Config",
  "trackId": "53",
  "centerline": [
    {
      "x": 1198.3,
      "y": 986.4,
      "distPct": 0
    },
    {
      "x": 744.0,
      "y": 984.6,
      "distPct": 0.1082
    },
    {
      "x": 743.1,
      "y": 984.4,
      "distPct": 0.1084
    },
    {
      "x": 730.14,
      "y": 981.68,
      "distPct": 0.1116
    },
    {
      "x": 695.25,
      "y": 973.48,
      "distPct": 0.1201
    },
    {
      "x": 642.81,
      "y": 959.45,
      "distPct": 0.1331
    },
    {
      "x": 577.2,
      "y": 939.3,
      "distPct": 0.1494
    },
    {
      "x": 505.6,
      "y": 913.79,
      "distPct": 0.1675
    },
    {
      "x": 425.2,
      "y": 880.11,
      "distPct": 0.1883
    },
    {
      "x": 341.65,
      "y": 837.98,
      "distPct": 0.2106
    },
    {
      "x": 260.6,
      "y": 787.1,
      "distPct": 0.2334
    },
    {
      "x": 245.19,
      "y": 773.23,
      "distPct": 0.2383
    },
    {
      "x": 225.25,
      "y": 749.92,
      "distPct": 0.2456
    },
    {
      "x": 203.06,
      "y": 717.88,
      "distPct": 0.2549
    },
    {
      "x": 180.9,
      "y": 677.8,
      "distPct": 0.2658
    },
    {
      "x": 163.28,
      "y": 636.14,
      "distPct": 0.2766
    },
    {
      "x": 148.58,
      "y": 585.51,
      "distPct": 0.2891
    },
    {
      "x": 140.51,
      "y": 527.4,
      "distPct": 0.3031
    },
    {
      "x": 142.8,
      "y": 463.3,
      "distPct": 0.3184
    },
    {
      "x": 154.9,
      "y": 402.66,
      "distPct": 0.3331
    },
    {
      "x": 174.64,
      "y": 346.56,
      "distPct": 0.3473
    },
    {
      "x": 201.93,
      "y": 295.21,
      "distPct": 0.3611
    },
    {
      "x": 236.7,
      "y": 248.8,
      "distPct": 0.3749
    },
    {
      "x": 280.43,
      "y": 206.29,
      "distPct": 0.3895
    },
    {
      "x": 331.24,
      "y": 170.47,
      "distPct": 0.4043
    },
    {
      "x": 388.93,
      "y": 141.45,
      "distPct": 0.4196
    },
    {
      "x": 453.3,
      "y": 119.3,
      "distPct": 0.4359
    },
    {
      "x": 453.6,
      "y": 119.2,
      "distPct": 0.4359
    },
    {
      "x": 497.16,
      "y": 109.87,
      "distPct": 0.4465
    },
    {
      "x": 545.48,
      "y": 101.62,
      "distPct": 0.4582
    },
    {
      "x": 592.48,
      "y": 95.74,
      "distPct": 0.4695
    },
    {
      "x": 632.1,
      "y": 93.5,
      "distPct": 0.479
    },
    {
      "x": 762.65,
      "y": 94.45,
      "distPct": 0.5101
    },
    {
      "x": 1008.94,
      "y": 96.56,
      "distPct": 0.5687
    },
    {
      "x": 1248.53,
      "y": 98.69,
      "distPct": 0.6258
    },
    {
      "x": 1359.0,
      "y": 99.7,
      "distPct": 0.6521
    },
    {
      "x": 1385.15,
      "y": 102.94,
      "distPct": 0.6584
    },
    {
      "x": 1442.55,
      "y": 113.74,
      "distPct": 0.6723
    },
    {
      "x": 1512.7,
      "y": 134.87,
      "distPct": 0.6897
    },
    {
      "x": 1577.1,
      "y": 169.1,
      "distPct": 0.7071
    },
    {
      "x": 1579.8,
      "y": 171.13,
      "distPct": 0.7079
    },
    {
      "x": 1582.52,
      "y": 173.17,
      "distPct": 0.7087
    },
    {
      "x": 1585.28,
      "y": 175.26,
      "distPct": 0.7096
    },
    {
      "x": 1588.1,
      "y": 177.4,
      "distPct": 0.7104
    },
    {
      "x": 1617.66,
      "y": 199.85,
      "distPct": 0.7192
    },
    {
      "x": 1648.99,
      "y": 226.01,
      "distPct": 0.729
    },
    {
      "x": 1680.45,
      "y": 257.06,
      "distPct": 0.7395
    },
    {
      "x": 1710.4,
      "y": 294.2,
      "distPct": 0.7509
    },
    {
      "x": 1740.1,
      "y": 344.37,
      "distPct": 0.7647
    },
    {
      "x": 1761.36,
      "y": 399.15,
      "distPct": 0.7787
    },
    {
      "x": 1774.31,
      "y": 458.96,
      "distPct": 0.7933
    },
    {
      "x": 1779.1,
      "y": 524.2,
      "distPct": 0.8089
    },
    {
      "x": 1778.79,
      "y": 537.18,
      "distPct": 0.812
    },
    {
      "x": 1775.39,
      "y": 567.6,
      "distPct": 0.8193
    },
    {
      "x": 1765.45,
      "y": 611.44,
      "distPct": 0.83
    },
    {
      "x": 1745.5,
      "y": 664.7,
      "distPct": 0.8435
    },
    {
      "x": 1728.22,
      "y": 697.82,
      "distPct": 0.8524
    },
    {
      "x": 1707.96,
      "y": 729.09,
      "distPct": 0.8613
    },
    {
      "x": 1684.88,
      "y": 758.31,
      "distPct": 0.8702
    },
    {
      "x": 1659.1,
      "y": 785.3,
      "distPct": 0.8791
    },
    {
      "x": 1622.62,
      "y": 816.61,
      "distPct": 0.8905
    },
    {
      "x": 1581.81,
      "y": 844.76,
      "distPct": 0.9023
    },
    {
      "x": 1536.83,
      "y": 869.63,
      "distPct": 0.9146
    },
    {
      "x": 1487.8,
      "y": 891.1,
      "distPct": 0.9273
    },
    {
      "x": 1487.6,
      "y": 891.2,
      "distPct": 0.9274
    },
    {
      "x": 1428.22,
      "y": 912.62,
      "distPct": 0.9424
    },
    {
      "x": 1344.97,
      "y": 941.69,
      "distPct": 0.9634
    },
    {
      "x": 1260.72,
      "y": 969.23,
      "distPct": 0.9845
    },
    {
      "x": 1198.3,
      "y": 986.1,
      "distPct": 0.9999
    },
    {
      "x": 1198.3,
      "y": 986.4,
      "distPct": 1.0
    }
  ],
  "bounds": {
    "xMin": 140.51,
    "xMax": 1779.1,
    "yMin": 93.5,
    "yMax": 986.4
  },
  "pointCount": 70,
  "source": "iTelemetry/iracing-tracks",
  "baseline": 0.946,
  "clockwise": true
}